svg2code/OLD_svg_elements.py
svg2code/__init__.py
svg2code/cli.py
svg2code/code_generator.py
svg2code/helpers.py
svg2code/svg_colors.py
svg2code/svg_parser.py
svg2code-0.3.1.dist-info/DESCRIPTION.rst
svg2code-0.3.1.dist-info/METADATA
svg2code-0.3.1.dist-info/RECORD
svg2code-0.3.1.dist-info/WHEEL
svg2code-0.3.1.dist-info/entry_points.txt
svg2code-0.3.1.dist-info/metadata.json
svg2code-0.3.1.dist-info/top_level.txt
