Metadata-Version: 2.0
Name: svg2code
Version: 0.3.1
Summary: SVG2Code - Code Generator
Home-page: https://github.com/TiagoBras/svg2code
Author: Tiago Bras
Author-email: tiagodsbras@gmail.com
License: MIT
Platform: UNKNOWN
Requires-Dist: Jinja2 (>=2.9.5)
